README.txt
setup.cfg
setup.py
Products/__init__.py
Products.JYUDynaPage.egg-info/PKG-INFO
Products.JYUDynaPage.egg-info/SOURCES.txt
Products.JYUDynaPage.egg-info/dependency_links.txt
Products.JYUDynaPage.egg-info/entry_points.txt
Products.JYUDynaPage.egg-info/namespace_packages.txt
Products.JYUDynaPage.egg-info/not-zip-safe
Products.JYUDynaPage.egg-info/requires.txt
Products.JYUDynaPage.egg-info/top_level.txt
Products/JYUDynaPage/README.txt
Products/JYUDynaPage/__init__.py
Products/JYUDynaPage/compile-locales.sh
Products/JYUDynaPage/config.py
Products/JYUDynaPage/configure.zcml
Products/JYUDynaPage/interfaces.py
Products/JYUDynaPage/utils.py
Products/JYUDynaPage/Extensions/__init__.py
Products/JYUDynaPage/Extensions/migrate.py
Products/JYUDynaPage/Extensions/migration.py
Products/JYUDynaPage/browser/__init__.py
Products/JYUDynaPage/browser/configure.zcml
Products/JYUDynaPage/browser/dynapage.css
Products/JYUDynaPage/browser/dynapage.gif
Products/JYUDynaPage/browser/dynapage.py
Products/JYUDynaPage/browser/dynapage_view.pt
Products/JYUDynaPage/browser/list_header.png
Products/JYUDynaPage/browser/list_title_bg.png
Products/JYUDynaPage/content/__init__.py
Products/JYUDynaPage/content/configure.zcml
Products/JYUDynaPage/content/dynapage.py
Products/JYUDynaPage/content/schemata.py
Products/JYUDynaPage/i18n/plone-en.po
Products/JYUDynaPage/i18n/plone-fi.po
Products/JYUDynaPage/locales/dynapage.pot
Products/JYUDynaPage/locales/fi/LC_MESSAGES/dynapage.po
Products/JYUDynaPage/profiles/default/cssregistry.xml
Products/JYUDynaPage/profiles/default/factorytool.xml
Products/JYUDynaPage/profiles/default/metadata.xml
Products/JYUDynaPage/profiles/default/skins.xml
Products/JYUDynaPage/profiles/default/types.xml
Products/JYUDynaPage/profiles/default/types/DynaPage.xml
Products/JYUDynaPage/skins/jyudynapage_templates/dynapage_rss.pt
Products/JYUDynaPage/skins/jyudynapage_templates/dynapage_rss.pt.metadata
Products/JYUDynaPage/skins/jyudynapage_templates/search_rss.pt
Products/JYUDynaPage/skins/jyudynapage_templates/search_rss.pt.metadata
Products/JYUDynaPage/tests/__init__.py
Products/JYUDynaPage/tests/base.py
Products/JYUDynaPage/tests/test_setup.py
docs/HISTORY.txt
docs/INSTALL.txt
docs/LICENSE.GPL
docs/LICENSE.txt