Metadata-Version: 1.0
Name: Products.JYUDynaPage
Version: 1.5.1
Summary: Plone page with configurable dynamic lists in top       and bottom of the content.
Home-page: http://svn.plone.org/svn/collective/Products.JYUDynaPage
Author: Jukka Ojaniemi
Author-email: jukka.ojaniemi@jyu.fi
License: GPL
Keywords: Products.JYUDynaPage JYUDynaPage DynaPage DynamicPage
Platform: UNKNOWN
Classifier: Framework :: Plone
Classifier: Programming Language :: Python
Classifier: Topic :: Software Development :: Libraries :: Python Modules
